samap/__init__.py
samap/_constants.py
samap/_logging.py
samap/exceptions.py
samap/utils.py
samap/analysis/__init__.py
samap/analysis/enrichment.py
samap/analysis/gene_pairs.py
samap/analysis/plotting.py
samap/analysis/scores.py
samap/core/__init__.py
samap/core/mapping.py
samap/io/__init__.py
sc_samap-2.0.2.dist-info/METADATA
sc_samap-2.0.2.dist-info/WHEEL
sc_samap-2.0.2.dist-info/licenses/LICENSE
sc_samap-2.0.2.dist-info/RECORD
