Metadata-Version: 2.4
Name: sc-samap
Version: 2.0.2
Summary: The SAMap algorithm
Project-URL: Homepage, https://github.com/atarashansky/SAMap
Project-URL: Documentation, https://github.com/atarashansky/SAMap
Project-URL: Repository, https://github.com/atarashansky/SAMap
Project-URL: Issues, https://github.com/atarashansky/SAMap/issues
Author-email: "Alexander J. Tarashansky" <tarashan@stanford.edu>
License-Expression: MIT
License-File: LICENSE
Keywords: analysis,bioinformatics,cross-species,manifold,mapping,reconstruction,scrnaseq,single-cell
Classifier: Development Status :: 4 - Beta
Classifier: Intended Audience :: Science/Research
Classifier: License :: OSI Approved :: MIT License
Classifier: Operating System :: OS Independent
Classifier: Programming Language :: Python :: 3
Classifier: Programming Language :: Python :: 3.11
Classifier: Programming Language :: Python :: 3.12
Classifier: Topic :: Scientific/Engineering :: Bio-Informatics
Requires-Python: >=3.11
Requires-Dist: dill>=0.3.7
Requires-Dist: h5py>=3.10.0
Requires-Dist: hnswlib>=0.8.0
Requires-Dist: leidenalg>=0.10.0
Requires-Dist: networkx>=3.0
Requires-Dist: numba>=0.59.0
Requires-Dist: numpy>=1.26.0
Requires-Dist: pandas>=2.0.0
Requires-Dist: sc-sam>=2.0.0
Requires-Dist: scanpy>=1.10.0
Requires-Dist: scipy>=1.11.0
Provides-Extra: all
Requires-Dist: samap[dev,viz]; extra == 'all'
Provides-Extra: dev
Requires-Dist: mypy>=1.8; extra == 'dev'
Requires-Dist: pre-commit>=3.6; extra == 'dev'
Requires-Dist: pytest-cov>=4.1; extra == 'dev'
Requires-Dist: pytest>=8.0; extra == 'dev'
Requires-Dist: ruff>=0.2; extra == 'dev'
Provides-Extra: viz
Requires-Dist: matplotlib>=3.8; extra == 'viz'
Requires-Dist: plotly>=5.18; extra == 'viz'
Requires-Dist: seaborn>=0.13; extra == 'viz'
